setup.py
virtualenvwrapper/__init__.py
virtualenvwrapper/gem.py
virtualenvwrapper.gem.egg-info/PKG-INFO
virtualenvwrapper.gem.egg-info/SOURCES.txt
virtualenvwrapper.gem.egg-info/dependency_links.txt
virtualenvwrapper.gem.egg-info/entry_points.txt
virtualenvwrapper.gem.egg-info/namespace_packages.txt
virtualenvwrapper.gem.egg-info/requires.txt
virtualenvwrapper.gem.egg-info/top_level.txt