Metadata-Version: 1.0
Name: virtualenvwrapper.gem
Version: 0.1
Summary: Plugin for virtualenvwrapper to automatically encapsulate inside the virtual environmentany gems installed when the venv is activated
Home-page: https://github.com/rach/virtualenvwrapper.gem
Author: Rach Belaid
Author-email: dev@ironbraces.com
License: UNKNOWN
Platform: UNKNOWN
